<?xml version="1.0" encoding="UTF-8"?>
<sport version="0.3">
	<name>Shooting—Mixed team trap—Shoot-off only</name>
	<discipline>Shooting</discipline>
	<event>Mixed team trap</event>
	<scorinator>Shoot-off only</scorinator>
	
	<paradigm>shooting</paradigm>
	<paradigmOptions>
		<int type="qualifyingAttempts">0</int>
		<list type="qualifyingAttemptTypes">
		</list>
		<int type="qualifyingDisplayDigits">0</int>
		<double type="qualifyingRankModifier">1.015</double>
		<double type="qualifyingRankAdjustmentFactor">0.75</double>
		
		<int type="shootoffDisplayDigits">0</int>
		<double type="shootoffRankModifier">2</double>
		
		<string type="useBestGroups">false</string>
		<string type="sortOrder">descending</string>
	</paradigmOptions>

	<dataPoints name="shootoffScore">
		<dataPoint pos="0">0</dataPoint>
		<dataPoint pos="0.3">0</dataPoint>
		<dataPoint pos="1">1</dataPoint>
	</dataPoints>
</sport>